{
  "type": "film/documentary",
  "model": {
    "name": "string",
    "release-year": 0,
    "nicknames": "string",
    "able-to-screen": "string",
    "screen-register": "string",
    "category": "string",
    "duration": "string",
    "tag": "string",
    "trailers": "string",
    "where-to-watch": "string",
    "official-website": "string",
    "more_info": false
  },
  "rows": [
    {
      "name": "HOME",
      "release-year": 2009,
      "nicknames": "家园",
      "able-to-screen": "",
      "screen-register": "email: jacqueline@goodplanet.org",
      "category": "Documentary/Drama",
      "duration": "1h 58m",
      "tag": "",
      "trailers": "https://www.youtube.com/watch?v=oDlbBy9vfgI",
      "where-to-watch": "https://www.youtube.com/watch?v=jqxENMKaeCU",
      "official-website": "",
      "more_info": true
    },
    {
      "name": "Chasing Ice",
      "release-year": 2012,
      "nicknames": "逐冰之旅",
      "able-to-screen": "",
      "screen-register": "https://chasingice.com/screenings/",
      "category": "Documentary",
      "duration": "1h 15m",
      "tag": "climate-change, glacier",
      "trailers": "https://www.youtube.com/watch?v=HqknAn_3QpI",
      "where-to-watch": "https://www.bilibili.com/video/BV1w7411o7ny/",
      "official-website": "https://chasingice.com/",
      "more_info": true
    },
    {
      "name": "Two Raging Grannies",
      "release-year": 2013,
      "nicknames": "造反阿嬤(ㄇㄛˊ)",
      "able-to-screen": "not sure yet",
      "screen-register": "",
      "category": "Documentary",
      "duration": "1h 18m",
      "tag": "finance",
      "trailers": [
        "https://www.youtube.com/watch?v=KnnNPxk3vgI",
        "https://www.youtube.com/watch?v=ccBzk5OG5Pc"
      ],
      "where-to-watch": "https://www.youtube.com/watch?v=yrOZ9fRQLog",
      "official-website": "",
      "more_info": false
    },
    {
      "name": "That Sugar Film",
      "release-year": 2014,
      "nicknames": "",
      "able-to-screen": "not sure yet",
      "screen-register": "",
      "category": "Documentary/Drama",
      "duration": "1h 42m",
      "tag": "food",
      "trailers": "https://www.youtube.com/watch?v=6uaWekLrilY",
      "where-to-watch": "https://www.youtube.com/watch?v=SNr71oGoZC8",
      "official-website": "",
      "more_info": false
    },
    {
      "name": "Demain",
      "release-year": 2015,
      "nicknames": "Tomorrow, 明天",
      "able-to-screen": "not sure yet",
      "screen-register": [
        "https://www.tomorrow-derfilm.de/en/where-can-we-see-film.html",
        "https://www.marsfilm.net/en/iletisim"
      ],
      "category": "Documentary",
      "duration": "1h 58m",
      "tag": "climate-change, finance, solution",
      "trailers": [
        "https://www.youtube.com/watch?v=F16SUg83Tlg",
        "https://movie.douban.com/trailers/206352/#content"
      ],
      "where-to-watch": [
        "https://www.youtube.com/watch?v=nXuu1pF0hOM",
        "https://www.bilibili.com/video/BV12h4y177DM"
      ],
      "official-website": "",
      "more_info": false
    },
    {
      "name": "Minimalism: A Documentary About the Important Things",
      "release-year": 2015,
      "nicknames": "极简主义：记录生命中的重要事物",
      "able-to-screen": "not sure yet",
      "screen-register": "",
      "category": "Documentary",
      "duration": "1h 19m",
      "tag": "finance",
      "trailers": "https://www.youtube.com/watch?v=0Co1Iptd4p4",
      "where-to-watch": "https://www.youtube.com/watch?v=J8DGjUv-Vjc",
      "official-website": "",
      "more_info": false
    },
    {
      "name": "The True Cost",
      "release-year": 2015,
      "nicknames": "真正的成本",
      "able-to-screen": "not sure yet",
      "screen-register": "email: jacqueline@goodplanet.org",
      "category": "Documentary/Drama",
      "duration": "1h 33m",
      "tag": "finance",
      "trailers": "https://www.youtube.com/watch?v=QPMU1VHgmEo",
      "where-to-watch": "https://www.youtube.com/watch?v=rwp0Bx0awoE",
      "official-website": "",
      "more_info": true
    },
    {
      "name": "Before the Flood",
      "release-year": 2016,
      "nicknames": "洪水泛滥之前",
      "able-to-screen": "string",
      "screen-register": "string",
      "category": "string",
      "duration": "string",
      "tag": "string",
      "trailers": "string",
      "where-to-watch": "string",
      "official-website": "string",
      "more_info": false
    },
    {
      "name": "Chasing Coral",
      "nicknames": "追逐珊瑚",
      "release-year": 2017,
      "category": "Documentary/Drama",
      "duration": "1h 33m",
      "tag": "climate-change, ocean",
      "trailers": "https://www.youtube.com/watch?v=b6fHA9R2cKI",
      "where-to-watch": "https://www.youtube.com/watch?v=aGGBGcjdjXA",
      "official-website": "https://chasingcoral.com/",
      "screen-register": "https://chasingcoral.com/screenings/",
      "more_info": true
    },
    {
      "name": "Jane",
      "release-year": 2017,
      "nicknames": "珍·古道尔的传奇一生",
      "able-to-screen": "not sure yet",
      "screen-register": "",
      "category": "string",
      "duration": "string",
      "tag": "string",
      "trailers": "string",
      "where-to-watch": "string",
      "official-website": "string",
      "more_info": false
    },
    {
      "name": "2040",
      "release-year": 2019,
      "nicknames": "",
      "able-to-screen": "free option",
      "screen-register": "https://theregenerators.org/2040/2040-host-a-screening/",
      "category": "Documentary",
      "duration": "1h 32m",
      "tag": "solution",
      "trailers": "https://www.youtube.com/watch?v=p-rTQ443akE",
      "where-to-watch": "https://www.bilibili.com/video/BV14t4y1Q7Wc/",
      "official-website": "string",
      "more_info": false
    },
    {
      "name": "Kiss the Ground",
      "release-year": 2020,
      "nicknames": "接吻地面",
      "able-to-screen": "free option",
      "screen-register": "https://kissthegroundmovie.com/host-a-screening/",
      "category": "string",
      "duration": "string",
      "tag": "string",
      "trailers": "string",
      "where-to-watch": "string",
      "official-website": "string",
      "more_info": false
    },
    {
      "name": "Outgrow the system",
      "release-year": 2024,
      "nicknames": "超越旧系统（暂译）",
      "able-to-screen": "free option",
      "screen-register": "https://docs.google.com/forms/d/e/1FAIpQLScTi32oQ4TiAJ-iCKYn_YvvsNKnvneu68lTnjx-olTSphGXfw/viewform",
      "category": "Documentary",
      "duration": "58m",
      "tag": "",
      "trailers": "https://www.youtube.com/watch?v=g7thOfXjGWM",
      "where-to-watch": "string",
      "official-website": "https://rafilm.se/outgrow-the-system",
      "more_info": false,
      "subtitle": true
    }
  ]
}